hypothesis_faker/__init__.py
hypothesis_faker/providers.py
hypothesis_faker/py.typed
hypothesis_faker/settings.py
hypothesis_faker/strategies.py
hypothesis_faker-0.1.13.dist-info/LICENSE
hypothesis_faker-0.1.13.dist-info/WHEEL
hypothesis_faker-0.1.13.dist-info/METADATA
hypothesis_faker-0.1.13.dist-info/RECORD
